docs/source/conf.py
redata/__init__.py
redata/commons/__init__.py
redata/commons/git_info.py
redata/commons/issue_request.py
redata/commons/logger.py
tests/__init__.py
tests/test_git_info.py
tests/test_logger.py
redata-0.5.0.dist-info/LICENSE
redata-0.5.0.dist-info/METADATA
redata-0.5.0.dist-info/WHEEL
redata-0.5.0.dist-info/top_level.txt
redata-0.5.0.dist-info/RECORD
