Metadata-Version: 2.1
Name: redata
Version: 0.5.0
Summary: Commons code used by ReDATA software
Home-page: https://github.com/UAL-RE/redata-commons/
Author: Yan Han
Author-email: yhan818@gmail.com
License: MIT License
Project-URL: Source, https://github.com/UAL-RE/redata-commons/
Project-URL: Tracker, https://github.com/UAL-RE/redata-commons/issues
Classifier: Development Status :: 4 - Beta
Classifier: Programming Language :: Python :: 3 :: Only
Classifier: Programming Language :: Python :: 3.8
Classifier: Programming Language :: Python :: 3.9
Requires-Python: >=3.8
License-File: LICENSE
Requires-Dist: pandas (==1.4.3)
Requires-Dist: tabulate (==0.8.10)
Requires-Dist: requests (==2.25.1)
